dizz-0.1.3.dist-info/METADATA
dizz-0.1.3.dist-info/WHEEL
dizz/__init__.py
dizz/dizz.cpython-38-aarch64-linux-gnu.so
dizz-0.1.3.dist-info/RECORD
